 [
    {
      "id": 1,
      "title": "3D Product Viewer",
      "description": "An interactive 3D product viewer built with Three.js.",
      "imageUrl": "/images/product-viewer.png",
      "link": "/3d-product-viewer"
    },
    {
      "id": 2,
      "title": "Solar System",
      "description": "Explore solar systems in 3D space.",
      "imageUrl": "/images/solar-system.png",
      "link": "/solar-system"
    },
    {
      "id": 3,
      "title": "Shoe Viewer",
      "description": "An interactive 3D shoe viewer with colors.",
      "imageUrl": "/images/shoe.png",
      "link": "/shoe-viewer"
    },
    {
      "id": 4,
      "title": "3d Solar System",
      "description": "An interactive 3D solar system.",
      "imageUrl": "/images/solar.png",
      "link": "/3d-solar-system"
    },
    {
      "id": 5,
      "title": "3D Interactive Drawer",
      "description": "An interactive 3D Drawer.",
      "imageUrl": "/images/drawer.png",
      "link": "/3d-drawer"
    }
]

